Lab4/lab4.v
module logic_tile(
    out, 
    clock, 
    in1, 
    in2, 
    in3, 
    in4, 
    in5
);
    input in1, in2, in3, in4, in5, clock ;
    output out ;
    reg out ;
    reg tem;
    reg tem2;
    reg [32:0] mem;
    always @(*) begin
        case({in5, in4, in3, in2, in1})
            5'b00000 : tem = mem[0] ;
            5'b00001 : tem = mem[1] ;
            5'b00010 : tem = mem[2] ;
            5'b00011 : tem = mem[3] ;
            5'b00100 : tem = mem[4] ;
            5'b00101 : tem = mem[5] ;
            5'b00110 : tem = mem[6] ;
            5'b00111 : tem = mem[7] ;
            5'b01000 : tem = mem[8] ;
            5'b01001 : tem = mem[9] ;
            5'b01010 : tem = mem[10] ;
            5'b01011 : tem = mem[11] ;
            5'b01100 : tem = mem[12] ;
            5'b01101 : tem = mem[13] ;
            5'b01110 : tem = mem[14] ;
            5'b01111 : tem = mem[15] ;
            5'b10000 : tem = mem[16] ;
            5'b10001 : tem = mem[17] ;
            5'b10010 : tem = mem[18] ;
            5'b10011 : tem = mem[19] ;
            5'b10100 : tem = mem[20] ;
            5'b10101 : tem = mem[21] ;
            5'b10110 : tem = mem[22] ;
            5'b10111 : tem = mem[23] ;
            5'b11000 : tem = mem[24] ;
            5'b11001 : tem = mem[25] ;
            5'b11010 : tem = mem[26] ;
            5'b11011 : tem = mem[27] ;
            5'b11100 : tem = mem[28] ;
            5'b11101 : tem = mem[29] ;
            5'b11110 : tem = mem[30] ;
            5'b11111 : tem = mem[31] ;
        endcase
    end
    always @(posedge clock) begin
        tem2 = tem;
    end
    always @(*) begin
        case (mem[32])
            1'b0 : out = tem ;
            1'b1 : out = tem2 ;
        endcase
    end
endmodule

module switch_box_4x4(
    out, 
    in);
    input [3: 0] in ;
    output [3:0] out ;
    reg [15:0] configure ;
    assign out[0] = configure[0]&in[0] | configure[1]&in[1] | configure[2]&in[2] | configure[3]&in[3] ;
    assign out[1] = configure[4]&in[0] | configure[5]&in[1] | configure[6]&in[2] | configure[7]&in[3] ;
    assign out[2] = configure[8]&in[0] | configure[9]&in[1] | configure[10]&in[2] | configure[11]&in[3] ;
    assign out[3] = configure[12]&in[0] | configure[13]&in[1] | configure[14]&in[2] | configure[15]&in[3] ;

endmodule

Lab4/testbench.v
module testbench(
);
    reg clock = 1'b0;
    reg in1 ,in2, in3, in4, in5;
    wire out;
    wire [3:0] out2;
    reg [3:0] in ;
    
    always #10 clock = ~clock ;
    logic_tile tile(out, clock, in1, in2, in3, in4, in5);
    switch_box_4x4 switch(out2, in);
    reg [31:0] tb_mem [0:2];
    initial begin
        $readmemh("info.mem", tb_mem);
        switch.configure[15:0] = tb_mem[2];
        tile.mem[32] = tb_mem[1];
        tile.mem[31:0] = tb_mem[0];
    end
    initial begin
        in1 = 1'b1;
        in2 = 1'b1;
        in3 = 1'b1;
        in4 = 1'b1;
        in5 = 1'b1;
        #16
        $display("output LT is %b", out);
        in1 = 1'b0;
        in2 = 1'b0;
        in3 = 1'b0;
        in4 = 1'b0;
        in5 = 1'b0;
        #16
        $display("output LT is %b", out);
        in1 = 1'b0;
        in2 = 1'b0;
        in3 = 1'b1;
        in4 = 1'b0;
        in5 = 1'b1;
        #16
        $display("output LT is %b", out); 
        in = 4'b1010;
        #10
        $display("output switch is %b", out2);
        in = 4'b1000;
        #10
        $display("output switch is %b", out2);
        in = 4'b1011;
        #10
        $display("output switch is %b", out2);
        in = 4'b0010;
        #10
        $display("output switch is %b", out2);
        $finish;
    end
    initial
    begin
        $dumpfile("dump.vcd");
        $dumpvars;
    end
endmodule

Lab4/dump.vcd
$date
	Sat Nov 14 18:49:19 2020
$end
$version
	Icarus Verilog
$end
$timescale
	1s
$end
$scope module testbench $end
$var wire 4 ! out2 [3:0] $end
$var wire 1 " out $end
$var reg 1 # clock $end
$var reg 4 $ in [3:0] $end
$var reg 1 % in1 $end
$var reg 1 & in2 $end
$var reg 1 ' in3 $end
$var reg 1 ( in4 $end
$var reg 1 ) in5 $end
$scope module switch $end
$var wire 4 * in [3:0] $end
$var wire 4 + out [3:0] $end
$var reg 16 , configure [15:0] $end
$upscope $end
$scope module tile $end
$var wire 1 # clock $end
$var wire 1 % in1 $end
$var wire 1 & in2 $end
$var wire 1 ' in3 $end
$var wire 1 ( in4 $end
$var wire 1 ) in5 $end
$var reg 33 - mem [32:0] $end
$var reg 1 " out $end
$var reg 1 . tem $end
$var reg 1 / tem2 $end
$upscope $end
$upscope $end
$enddefinitions $end
#0
$dumpvars
x/
1.
b11111111111111111111111111111110 -
b1000010000100001 ,
bx +
bx *
1)
1(
1'
1&
1%
bx $
0#
1"
bx !
$end
#10
1/
1#
#16
0"
0.
0)
0(
0'
0&
0%
#20
0#
#30
0/
1#
#32
1"
1.
1)
1'
#40
0#
#48
b1010 !
b1010 +
b1010 $
b1010 *
#50
1/
1#
#58
b1000 !
b1000 +
b1000 $
b1000 *
#60
0#
#68
b1011 !
b1011 +
b1011 $
b1011 *
#70
1#
#78
b10 !
b10 +
b10 $
b10 *
