Lab3/lab3_add.v
module full_adder (
    sum,
    cout,
    a,
    b,
    cin
);
    input a, b, cin ;
    output sum, cout;
    wire axb ;
    assign #4 sum = a^b^cin;
    assign #3 cout = (a&b) | (a&cin) | (b&cin);
endmodule

module add16_rc (
    sum16, cout, a16, b16, cin
);
    input [15:0]a16;
    input [15:0] b16;
    input cin;
    wire [16:0] carry;
    assign carry[0] = cin;
    output [15:0]sum16;
    output cout;
    genvar i;
    generate for (i = 0;i<16 ;i=i+1 ) begin
        full_adder g1(sum16[i], carry[i+1], a16[i], b16[i], carry[i]);
    end
    endgenerate
    assign cout = carry[16];
endmodule

module carry_generator (
    couts, p, g, cin
);
    input [3:0] g;
    input [3:0] p;
    input cin;
    output [3:0] couts;
    assign #2 couts[0] = g[0]|(p[0]&cin);
    assign #2 couts[1] = g[1]|(p[1]&couts[0]);
    assign #2 couts[2] = g[2]|(p[2]&couts[1]);
    assign #2 couts[3] = g[3]|(p[3]&couts[2]);
endmodule

module full_adder_pg (
    sum, cout, p, g, a, b, cin
);
    input a, b, cin;
    output sum, cout, p, g;
    assign #4 sum = a^b^cin;
    assign #1 g = a&b;
    assign #1 p = a|b;
    assign #1 cout = g|(p&cin);
endmodule

module add4_cla (
    sum4, cout, a4, b4, cin
);
    input [3:0]a4;
    input [3:0] b4;
    input cin;
    wire [4:0] carry;
    assign carry[0] = cin;
    output [3:0]sum4;
    output cout;
    wire [3:0] g;
    wire [3:0] p;
    genvar i;
    generate
        for (i = 0; i<4 ;i=i+1 ) begin
            full_adder_pg pg1( , ,p[i], g[i], a4[i], b4[i], );
        end
    endgenerate
    wire [3:0]couts;
    carry_generator cry(couts, p, g, cin);
    wire [4:0] final;
    assign #4 sum4[0] = a4[0]^b4[0]^cin;
    assign #4 sum4[1] = a4[1]^b4[1]^couts[0];
    assign  #4 sum4[2] = a4[2]^b4[2]^couts[1];
    assign  #4 sum4[3] = a4[3]^b4[3]^couts[2];
    assign cout = couts[3];
endmodule

module add16_cla (
    sum16, cout, a16, b16, cin
);
    input [15:0] a16;
    input [15:0] b16;
    input cin;
    output [15:0] sum16;
    output cout;
    wire [16:0] carry;
    wire [3:0] gstr;
    wire [3:0] pstr;
    wire [15:0] g;
    wire [15: 0] p;
    wire [4:0] couts;
    assign couts[0] = cin;
    genvar i;
    generate
        for (i =0 ;i<16 ;i=i+1 ) begin
            full_adder_pg g1( , , p[i], g[i], a16[i], b16[i], );
        end
    endgenerate
    genvar j;
    generate for (j =0 ;j<13 ; j=j+4) begin
        assign  gstr[j/4] = g[j+3] | g[j+2]&p[j+3] | g[j+1]&p[j+2]&p[j+3] | g[j]&p[j+1]&p[j+2]&p[j+3];
        assign  pstr[j/4] = p[j]&p[j+1]&p[j+2]&p[j+3];
        //assign couts[1+j/4] = gstr[j/4]|(couts[j/4]&p[j/4]);
    end
    endgenerate
    assign #2 couts[1] = gstr[0] | couts[0]&pstr[0];
    assign #4 couts[2] = gstr[1] | gstr[0]&pstr[1] | couts[0]&pstr[0]&pstr[1];
    assign #4 couts[3] = gstr[2] | gstr[1]&pstr[2] | gstr[0]&pstr[1]&pstr[2] | couts[0]&pstr[0]&pstr[1]&pstr[2];
    assign #6 couts[4] = gstr[3] | gstr[1]&pstr[2]&pstr[3] | gstr[0]&pstr[1]&pstr[2]&pstr[3] | couts[0]&pstr[0]&pstr[1]&pstr[2]&pstr[3];
    add4_cla f1(sum16[3:0], , a16[3:0], b16[3:0], couts[0]);
    add4_cla f2(sum16[7:4], , a16[7:4], b16[7:4], couts[1]);
    add4_cla f3(sum16[11:8], , a16[11:8], b16[11:8], couts[2]);
    add4_cla f4(sum16[15:12], , a16[15:12], b16[15:12], couts[3]);
    assign cout = couts[4];
endmodule

Lab3/testbench.v
module testbench (
);
    reg[15:0] rin1; 
    reg[15:0] rin2;
    reg rin3;
    wire[15:0] wout;
    wire o;
    reg[15:0] rinb1; 
    reg[15:0] rinb2;
    reg rinb3;
    wire[15:0] woutb;
    wire ob;
    add16_cla full(wout, o, rin1, rin2, rin3);
    add16_rc long(woutb, ob, rinb1, rinb2, rinb3);
    initial begin
        rin1 = 16'b0000000000000000; 
        rin2 = 16'b0000000000000000;
        rin3 = 1'b0;
        #10
        $display("sum : %b  cout : %b  input1: %b  input2: %b  cin: %b", wout, o, rin1, rin2, rin3);
        rin1 = 16'b0000000000000000; 
        rin2 = 16'b0000000000000000;
        rin3 = 1'b1;
        #10
        $display("sum : %b  cout : %b  input1: %b  input2: %b  cin: %b", wout, o, rin1, rin2, rin3);
        rin1 = 16'b1111111111111111; 
        rin2 = 16'b0000000000000001;
        rin3 = 1'b0;
        #10
        $display("sum : %b  cout : %b  input1: %b  input2: %b  cin: %b", wout, o, rin1, rin2, rin3);
        rin1 = 16'b0011111000000000; 
        rin2 = 16'b0000111110000000;
        rin3 = 1'b0;
        #10
        $display("sum : %b  cout : %b  input1: %b  input2: %b  cin: %b", wout, o, rin1, rin2, rin3);
        rin1 = 16'b1100000000011100; 
        rin2 = 16'b0000011110000000;
        rin3 = 1'b0;
        #10
        $display("sum : %b  cout : %b  input1: %b  input2: %b  cin: %b", wout, o, rin1, rin2, rin3);
        rin1 = 16'b0000000000000000; 
        rin2 = 16'b0000000000000000;
        rin3 = 1'b0;
        #10
        $display("sum : %b  cout : %b  input1: %b  input2: %b  cin: %b", wout, o, rin1, rin2, rin3);
        rin1 = 16'b1111111111111111; 
        rin2 = 16'b1111111111111111;
        rin3 = 1'b0;
        #10
        $display("sum : %b  cout : %b  input1: %b  input2: %b  cin: %b", wout, o, rin1, rin2, rin3);
        rin1 = 16'b1010101010101010; 
        rin2 = 16'b0000000000000001;
        rin3 = 1'b1;
        #10
        $display("sum : %b  cout : %b  input1: %b  input2: %b  cin: %b", wout, o, rin1, rin2, rin3);
    end
    initial begin
        rinb1 = 16'b0000000000000000; 
        rinb2 = 16'b0000000000000000;
        rinb3 = 1'b0;
        #10
        $display("RC sum : %b  cout : %b  input1: %b  input2: %b  cin: %b", woutb, ob, rinb1, rinb2, rinb3);
        rinb1 = 16'b0000000000000000; 
        rinb2 = 16'b0000000000000000;
        rinb3 = 1'b1;
        #10
        $display("RC sum : %b  cout : %b  input1: %b  input2: %b  cin: %b", woutb, ob, rinb1, rinb2, rinb3);
        rinb1 = 16'b1111111111111111; 
        rinb2 = 16'b0000000000000001;
        rinb3 = 1'b0;
        #10
        $display("RC sum : %b  cout : %b  input1: %b  input2: %b  cin: %b", woutb, ob, rinb1, rinb2, rinb3);
        rinb1 = 16'b0011111000000000; 
        rinb2 = 16'b0000111110000000;
        rinb3 = 1'b0;
        #10
        $display("RC sum : %b  cout : %b  input1: %b  input2: %b  cin: %b", woutb, ob, rinb1, rinb2, rinb3);
        rinb1 = 16'b1100000000011100; 
        rinb2 = 16'b0000011110000000;
        rinb3 = 1'b0;
        #10
        $display("RC sum : %b  cout : %b  input1: %b  input2: %b  cin: %b", woutb, ob, rinb1, rinb2, rinb3);
        rinb1 = 16'b0000000000000000; 
        rinb2 = 16'b0000000000000000;
        rinb3 = 1'b0;
        #10
        $display("RC sum : %b  cout : %b  input1: %b  input2: %b  cin: %b", woutb, ob, rinb1, rinb2, rinb3);
        rinb1 = 16'b1111111111111111; 
        rinb2 = 16'b1111111111111111;
        rinb3 = 1'b0;
        #10
        $display("RC sum : %b  cout : %b  input1: %b  input2: %b  cin: %b", woutb, ob, rinb1, rinb2, rinb3);
        rinb1 = 16'b1010101010101010; 
        rinb2 = 16'b0000000000000001;
        rinb3 = 1'b1;
        #10
        $display("RC sum : %b  cout : %b  input1: %b  input2: %b  cin: %b", woutb, ob, rinb1, rinb2, rinb3);
    end
    initial
    begin
        $dumpfile("dump.vcd");
        $dumpvars;
    end
endmodule

Lab3/dump.vcd
$date
	Tue Oct 06 21:49:42 2020
$end
$version
	Icarus Verilog
$end
$timescale
	1s
$end
$scope module testbench $end
$var wire 16 ! woutb [15:0] $end
$var wire 16 " wout [15:0] $end
$var wire 1 # ob $end
$var wire 1 $ o $end
$var reg 16 % rin1 [15:0] $end
$var reg 16 & rin2 [15:0] $end
$var reg 1 ' rin3 $end
$var reg 16 ( rinb1 [15:0] $end
$var reg 16 ) rinb2 [15:0] $end
$var reg 1 * rinb3 $end
$scope module full $end
$var wire 16 + a16 [15:0] $end
$var wire 16 , b16 [15:0] $end
$var wire 1 ' cin $end
$var wire 16 - sum16 [15:0] $end
$var wire 4 . pstr [3:0] $end
$var wire 16 / p [15:0] $end
$var wire 4 0 gstr [3:0] $end
$var wire 16 1 g [15:0] $end
$var wire 5 2 couts [4:0] $end
$var wire 1 $ cout $end
$scope begin genblk1[0] $end
$scope module g1 $end
$var wire 1 3 a $end
$var wire 1 4 b $end
$var wire 1 5 cin $end
$var wire 1 6 cout $end
$var wire 1 7 g $end
$var wire 1 8 p $end
$var wire 1 9 sum $end
$upscope $end
$upscope $end
$scope begin genblk1[1] $end
$scope module g1 $end
$var wire 1 : a $end
$var wire 1 ; b $end
$var wire 1 < cin $end
$var wire 1 = cout $end
$var wire 1 > g $end
$var wire 1 ? p $end
$var wire 1 @ sum $end
$upscope $end
$upscope $end
$scope begin genblk1[2] $end
$scope module g1 $end
$var wire 1 A a $end
$var wire 1 B b $end
$var wire 1 C cin $end
$var wire 1 D cout $end
$var wire 1 E g $end
$var wire 1 F p $end
$var wire 1 G sum $end
$upscope $end
$upscope $end
$scope begin genblk1[3] $end
$scope module g1 $end
$var wire 1 H a $end
$var wire 1 I b $end
$var wire 1 J cin $end
$var wire 1 K cout $end
$var wire 1 L g $end
$var wire 1 M p $end
$var wire 1 N sum $end
$upscope $end
$upscope $end
$scope begin genblk1[4] $end
$scope module g1 $end
$var wire 1 O a $end
$var wire 1 P b $end
$var wire 1 Q cin $end
$var wire 1 R cout $end
$var wire 1 S g $end
$var wire 1 T p $end
$var wire 1 U sum $end
$upscope $end
$upscope $end
$scope begin genblk1[5] $end
$scope module g1 $end
$var wire 1 V a $end
$var wire 1 W b $end
$var wire 1 X cin $end
$var wire 1 Y cout $end
$var wire 1 Z g $end
$var wire 1 [ p $end
$var wire 1 \ sum $end
$upscope $end
$upscope $end
$scope begin genblk1[6] $end
$scope module g1 $end
$var wire 1 ] a $end
$var wire 1 ^ b $end
$var wire 1 _ cin $end
$var wire 1 ` cout $end
$var wire 1 a g $end
$var wire 1 b p $end
$var wire 1 c sum $end
$upscope $end
$upscope $end
$scope begin genblk1[7] $end
$scope module g1 $end
$var wire 1 d a $end
$var wire 1 e b $end
$var wire 1 f cin $end
$var wire 1 g cout $end
$var wire 1 h g $end
$var wire 1 i p $end
$var wire 1 j sum $end
$upscope $end
$upscope $end
$scope begin genblk1[8] $end
$scope module g1 $end
$var wire 1 k a $end
$var wire 1 l b $end
$var wire 1 m cin $end
$var wire 1 n cout $end
$var wire 1 o g $end
$var wire 1 p p $end
$var wire 1 q sum $end
$upscope $end
$upscope $end
$scope begin genblk1[9] $end
$scope module g1 $end
$var wire 1 r a $end
$var wire 1 s b $end
$var wire 1 t cin $end
$var wire 1 u cout $end
$var wire 1 v g $end
$var wire 1 w p $end
$var wire 1 x sum $end
$upscope $end
$upscope $end
$scope begin genblk1[10] $end
$scope module g1 $end
$var wire 1 y a $end
$var wire 1 z b $end
$var wire 1 { cin $end
$var wire 1 | cout $end
$var wire 1 } g $end
$var wire 1 ~ p $end
$var wire 1 !" sum $end
$upscope $end
$upscope $end
$scope begin genblk1[11] $end
$scope module g1 $end
$var wire 1 "" a $end
$var wire 1 #" b $end
$var wire 1 $" cin $end
$var wire 1 %" cout $end
$var wire 1 &" g $end
$var wire 1 '" p $end
$var wire 1 (" sum $end
$upscope $end
$upscope $end
$scope begin genblk1[12] $end
$scope module g1 $end
$var wire 1 )" a $end
$var wire 1 *" b $end
$var wire 1 +" cin $end
$var wire 1 ," cout $end
$var wire 1 -" g $end
$var wire 1 ." p $end
$var wire 1 /" sum $end
$upscope $end
$upscope $end
$scope begin genblk1[13] $end
$scope module g1 $end
$var wire 1 0" a $end
$var wire 1 1" b $end
$var wire 1 2" cin $end
$var wire 1 3" cout $end
$var wire 1 4" g $end
$var wire 1 5" p $end
$var wire 1 6" sum $end
$upscope $end
$upscope $end
$scope begin genblk1[14] $end
$scope module g1 $end
$var wire 1 7" a $end
$var wire 1 8" b $end
$var wire 1 9" cin $end
$var wire 1 :" cout $end
$var wire 1 ;" g $end
$var wire 1 <" p $end
$var wire 1 =" sum $end
$upscope $end
$upscope $end
$scope begin genblk1[15] $end
$scope module g1 $end
$var wire 1 >" a $end
$var wire 1 ?" b $end
$var wire 1 @" cin $end
$var wire 1 A" cout $end
$var wire 1 B" g $end
$var wire 1 C" p $end
$var wire 1 D" sum $end
$upscope $end
$upscope $end
$scope begin genblk2[0] $end
$upscope $end
$scope begin genblk2[4] $end
$upscope $end
$scope begin genblk2[8] $end
$upscope $end
$scope begin genblk2[12] $end
$upscope $end
$scope module f1 $end
$var wire 4 E" a4 [3:0] $end
$var wire 4 F" b4 [3:0] $end
$var wire 1 G" cin $end
$var wire 4 H" sum4 [3:0] $end
$var wire 4 I" p [3:0] $end
$var wire 4 J" g [3:0] $end
$var wire 4 K" couts [3:0] $end
$var wire 1 L" cout $end
$var wire 5 M" carry [4:0] $end
$scope begin genblk1[0] $end
$scope module pg1 $end
$var wire 1 N" a $end
$var wire 1 O" b $end
$var wire 1 P" cin $end
$var wire 1 Q" cout $end
$var wire 1 R" g $end
$var wire 1 S" p $end
$var wire 1 T" sum $end
$upscope $end
$upscope $end
$scope begin genblk1[1] $end
$scope module pg1 $end
$var wire 1 U" a $end
$var wire 1 V" b $end
$var wire 1 W" cin $end
$var wire 1 X" cout $end
$var wire 1 Y" g $end
$var wire 1 Z" p $end
$var wire 1 [" sum $end
$upscope $end
$upscope $end
$scope begin genblk1[2] $end
$scope module pg1 $end
$var wire 1 \" a $end
$var wire 1 ]" b $end
$var wire 1 ^" cin $end
$var wire 1 _" cout $end
$var wire 1 `" g $end
$var wire 1 a" p $end
$var wire 1 b" sum $end
$upscope $end
$upscope $end
$scope begin genblk1[3] $end
$scope module pg1 $end
$var wire 1 c" a $end
$var wire 1 d" b $end
$var wire 1 e" cin $end
$var wire 1 f" cout $end
$var wire 1 g" g $end
$var wire 1 h" p $end
$var wire 1 i" sum $end
$upscope $end
$upscope $end
$scope module cry $end
$var wire 1 G" cin $end
$var wire 4 j" g [3:0] $end
$var wire 4 k" p [3:0] $end
$var wire 4 l" couts [3:0] $end
$upscope $end
$upscope $end
$scope module f2 $end
$var wire 4 m" a4 [3:0] $end
$var wire 4 n" b4 [3:0] $end
$var wire 1 o" cin $end
$var wire 4 p" sum4 [3:0] $end
$var wire 4 q" p [3:0] $end
$var wire 4 r" g [3:0] $end
$var wire 4 s" couts [3:0] $end
$var wire 1 t" cout $end
$var wire 5 u" carry [4:0] $end
$scope begin genblk1[0] $end
$scope module pg1 $end
$var wire 1 v" a $end
$var wire 1 w" b $end
$var wire 1 x" cin $end
$var wire 1 y" cout $end
$var wire 1 z" g $end
$var wire 1 {" p $end
$var wire 1 |" sum $end
$upscope $end
$upscope $end
$scope begin genblk1[1] $end
$scope module pg1 $end
$var wire 1 }" a $end
$var wire 1 ~" b $end
$var wire 1 !# cin $end
$var wire 1 "# cout $end
$var wire 1 ## g $end
$var wire 1 $# p $end
$var wire 1 %# sum $end
$upscope $end
$upscope $end
$scope begin genblk1[2] $end
$scope module pg1 $end
$var wire 1 &# a $end
$var wire 1 '# b $end
$var wire 1 (# cin $end
$var wire 1 )# cout $end
$var wire 1 *# g $end
$var wire 1 +# p $end
$var wire 1 ,# sum $end
$upscope $end
$upscope $end
$scope begin genblk1[3] $end
$scope module pg1 $end
$var wire 1 -# a $end
$var wire 1 .# b $end
$var wire 1 /# cin $end
$var wire 1 0# cout $end
$var wire 1 1# g $end
$var wire 1 2# p $end
$var wire 1 3# sum $end
$upscope $end
$upscope $end
$scope module cry $end
$var wire 1 o" cin $end
$var wire 4 4# g [3:0] $end
$var wire 4 5# p [3:0] $end
$var wire 4 6# couts [3:0] $end
$upscope $end
$upscope $end
$scope module f3 $end
$var wire 4 7# a4 [3:0] $end
$var wire 4 8# b4 [3:0] $end
$var wire 1 9# cin $end
$var wire 4 :# sum4 [3:0] $end
$var wire 4 ;# p [3:0] $end
$var wire 4 <# g [3:0] $end
$var wire 4 =# couts [3:0] $end
$var wire 1 ># cout $end
$var wire 5 ?# carry [4:0] $end
$scope begin genblk1[0] $end
$scope module pg1 $end
$var wire 1 @# a $end
$var wire 1 A# b $end
$var wire 1 B# cin $end
$var wire 1 C# cout $end
$var wire 1 D# g $end
$var wire 1 E# p $end
$var wire 1 F# sum $end
$upscope $end
$upscope $end
$scope begin genblk1[1] $end
$scope module pg1 $end
$var wire 1 G# a $end
$var wire 1 H# b $end
$var wire 1 I# cin $end
$var wire 1 J# cout $end
$var wire 1 K# g $end
$var wire 1 L# p $end
$var wire 1 M# sum $end
$upscope $end
$upscope $end
$scope begin genblk1[2] $end
$scope module pg1 $end
$var wire 1 N# a $end
$var wire 1 O# b $end
$var wire 1 P# cin $end
$var wire 1 Q# cout $end
$var wire 1 R# g $end
$var wire 1 S# p $end
$var wire 1 T# sum $end
$upscope $end
$upscope $end
$scope begin genblk1[3] $end
$scope module pg1 $end
$var wire 1 U# a $end
$var wire 1 V# b $end
$var wire 1 W# cin $end
$var wire 1 X# cout $end
$var wire 1 Y# g $end
$var wire 1 Z# p $end
$var wire 1 [# sum $end
$upscope $end
$upscope $end
$scope module cry $end
$var wire 1 9# cin $end
$var wire 4 \# g [3:0] $end
$var wire 4 ]# p [3:0] $end
$var wire 4 ^# couts [3:0] $end
$upscope $end
$upscope $end
$scope module f4 $end
$var wire 4 _# a4 [3:0] $end
$var wire 4 `# b4 [3:0] $end
$var wire 1 a# cin $end
$var wire 4 b# sum4 [3:0] $end
$var wire 4 c# p [3:0] $end
$var wire 4 d# g [3:0] $end
$var wire 4 e# couts [3:0] $end
$var wire 1 f# cout $end
$var wire 5 g# carry [4:0] $end
$scope begin genblk1[0] $end
$scope module pg1 $end
$var wire 1 h# a $end
$var wire 1 i# b $end
$var wire 1 j# cin $end
$var wire 1 k# cout $end
$var wire 1 l# g $end
$var wire 1 m# p $end
$var wire 1 n# sum $end
$upscope $end
$upscope $end
$scope begin genblk1[1] $end
$scope module pg1 $end
$var wire 1 o# a $end
$var wire 1 p# b $end
$var wire 1 q# cin $end
$var wire 1 r# cout $end
$var wire 1 s# g $end
$var wire 1 t# p $end
$var wire 1 u# sum $end
$upscope $end
$upscope $end
$scope begin genblk1[2] $end
$scope module pg1 $end
$var wire 1 v# a $end
$var wire 1 w# b $end
$var wire 1 x# cin $end
$var wire 1 y# cout $end
$var wire 1 z# g $end
$var wire 1 {# p $end
$var wire 1 |# sum $end
$upscope $end
$upscope $end
$scope begin genblk1[3] $end
$scope module pg1 $end
$var wire 1 }# a $end
$var wire 1 ~# b $end
$var wire 1 !$ cin $end
$var wire 1 "$ cout $end
$var wire 1 #$ g $end
$var wire 1 $$ p $end
$var wire 1 %$ sum $end
$upscope $end
$upscope $end
$scope module cry $end
$var wire 1 a# cin $end
$var wire 4 &$ g [3:0] $end
$var wire 4 '$ p [3:0] $end
$var wire 4 ($ couts [3:0] $end
$upscope $end
$upscope $end
$upscope $end
$scope module long $end
$var wire 16 )$ a16 [15:0] $end
$var wire 16 *$ b16 [15:0] $end
$var wire 1 * cin $end
$var wire 16 +$ sum16 [15:0] $end
$var wire 1 # cout $end
$var wire 17 ,$ carry [16:0] $end
$scope begin genblk1[0] $end
$scope module g1 $end
$var wire 1 -$ a $end
$var wire 1 .$ b $end
$var wire 1 /$ cin $end
$var wire 1 0$ cout $end
$var wire 1 1$ sum $end
$upscope $end
$upscope $end
$scope begin genblk1[1] $end
$scope module g1 $end
$var wire 1 2$ a $end
$var wire 1 3$ b $end
$var wire 1 4$ cin $end
$var wire 1 5$ cout $end
$var wire 1 6$ sum $end
$upscope $end
$upscope $end
$scope begin genblk1[2] $end
$scope module g1 $end
$var wire 1 7$ a $end
$var wire 1 8$ b $end
$var wire 1 9$ cin $end
$var wire 1 :$ cout $end
$var wire 1 ;$ sum $end
$upscope $end
$upscope $end
$scope begin genblk1[3] $end
$scope module g1 $end
$var wire 1 <$ a $end
$var wire 1 =$ b $end
$var wire 1 >$ cin $end
$var wire 1 ?$ cout $end
$var wire 1 @$ sum $end
$upscope $end
$upscope $end
$scope begin genblk1[4] $end
$scope module g1 $end
$var wire 1 A$ a $end
$var wire 1 B$ b $end
$var wire 1 C$ cin $end
$var wire 1 D$ cout $end
$var wire 1 E$ sum $end
$upscope $end
$upscope $end
$scope begin genblk1[5] $end
$scope module g1 $end
$var wire 1 F$ a $end
$var wire 1 G$ b $end
$var wire 1 H$ cin $end
$var wire 1 I$ cout $end
$var wire 1 J$ sum $end
$upscope $end
$upscope $end
$scope begin genblk1[6] $end
$scope module g1 $end
$var wire 1 K$ a $end
$var wire 1 L$ b $end
$var wire 1 M$ cin $end
$var wire 1 N$ cout $end
$var wire 1 O$ sum $end
$upscope $end
$upscope $end
$scope begin genblk1[7] $end
$scope module g1 $end
$var wire 1 P$ a $end
$var wire 1 Q$ b $end
$var wire 1 R$ cin $end
$var wire 1 S$ cout $end
$var wire 1 T$ sum $end
$upscope $end
$upscope $end
$scope begin genblk1[8] $end
$scope module g1 $end
$var wire 1 U$ a $end
$var wire 1 V$ b $end
$var wire 1 W$ cin $end
$var wire 1 X$ cout $end
$var wire 1 Y$ sum $end
$upscope $end
$upscope $end
$scope begin genblk1[9] $end
$scope module g1 $end
$var wire 1 Z$ a $end
$var wire 1 [$ b $end
$var wire 1 \$ cin $end
$var wire 1 ]$ cout $end
$var wire 1 ^$ sum $end
$upscope $end
$upscope $end
$scope begin genblk1[10] $end
$scope module g1 $end
$var wire 1 _$ a $end
$var wire 1 `$ b $end
$var wire 1 a$ cin $end
$var wire 1 b$ cout $end
$var wire 1 c$ sum $end
$upscope $end
$upscope $end
$scope begin genblk1[11] $end
$scope module g1 $end
$var wire 1 d$ a $end
$var wire 1 e$ b $end
$var wire 1 f$ cin $end
$var wire 1 g$ cout $end
$var wire 1 h$ sum $end
$upscope $end
$upscope $end
$scope begin genblk1[12] $end
$scope module g1 $end
$var wire 1 i$ a $end
$var wire 1 j$ b $end
$var wire 1 k$ cin $end
$var wire 1 l$ cout $end
$var wire 1 m$ sum $end
$upscope $end
$upscope $end
$scope begin genblk1[13] $end
$scope module g1 $end
$var wire 1 n$ a $end
$var wire 1 o$ b $end
$var wire 1 p$ cin $end
$var wire 1 q$ cout $end
$var wire 1 r$ sum $end
$upscope $end
$upscope $end
$scope begin genblk1[14] $end
$scope module g1 $end
$var wire 1 s$ a $end
$var wire 1 t$ b $end
$var wire 1 u$ cin $end
$var wire 1 v$ cout $end
$var wire 1 w$ sum $end
$upscope $end
$upscope $end
$scope begin genblk1[15] $end
$scope module g1 $end
$var wire 1 x$ a $end
$var wire 1 y$ b $end
$var wire 1 z$ cin $end
$var wire 1 {$ cout $end
$var wire 1 |$ sum $end
$upscope $end
$upscope $end
$upscope $end
$upscope $end
$enddefinitions $end
#0
$dumpvars
x|$
x{$
xz$
0y$
0x$
xw$
xv$
xu$
0t$
0s$
xr$
xq$
xp$
0o$
0n$
xm$
xl$
xk$
0j$
0i$
xh$
xg$
xf$
0e$
0d$
xc$
xb$
xa$
0`$
0_$
x^$
x]$
x\$
0[$
0Z$
xY$
xX$
xW$
0V$
0U$
xT$
xS$
xR$
0Q$
0P$
xO$
xN$
xM$
0L$
0K$
xJ$
xI$
xH$
0G$
0F$
xE$
xD$
xC$
0B$
0A$
x@$
x?$
x>$
0=$
0<$
x;$
x:$
x9$
08$
07$
x6$
x5$
x4$
03$
02$
x1$
x0$
0/$
0.$
0-$
bx0 ,$
bx +$
b0 *$
b0 )$
bx ($
bx '$
bx &$
x%$
x$$
x#$
x"$
z!$
0~#
0}#
x|#
x{#
xz#
xy#
zx#
0w#
0v#
xu#
xt#
xs#
xr#
zq#
0p#
0o#
xn#
xm#
xl#
xk#
zj#
0i#
0h#
bzx g#
xf#
bx e#
bx d#
bx c#
bx b#
xa#
b0 `#
b0 _#
bx ^#
bx ]#
bx \#
x[#
xZ#
xY#
xX#
zW#
0V#
0U#
xT#
xS#
xR#
xQ#
zP#
0O#
0N#
xM#
xL#
xK#
xJ#
zI#
0H#
0G#
xF#
xE#
xD#
xC#
zB#
0A#
0@#
bzx ?#
x>#
bx =#
bx <#
bx ;#
bx :#
x9#
b0 8#
b0 7#
bx 6#
bx 5#
bx 4#
x3#
x2#
x1#
x0#
z/#
0.#
0-#
x,#
x+#
x*#
x)#
z(#
0'#
0&#
x%#
x$#
x##
x"#
z!#
0~"
0}"
x|"
x{"
xz"
xy"
zx"
0w"
0v"
bzx u"
xt"
bx s"
bx r"
bx q"
bx p"
xo"
b0 n"
b0 m"
bx l"
bx k"
bx j"
xi"
xh"
xg"
xf"
ze"
0d"
0c"
xb"
xa"
x`"
x_"
z^"
0]"
0\"
x["
xZ"
xY"
xX"
zW"
0V"
0U"
xT"
xS"
xR"
xQ"
zP"
0O"
0N"
bz0 M"
xL"
bx K"
bx J"
bx I"
bx H"
0G"
b0 F"
b0 E"
xD"
xC"
xB"
xA"
z@"
0?"
0>"
x="
x<"
x;"
x:"
z9"
08"
07"
x6"
x5"
x4"
x3"
z2"
01"
00"
x/"
x."
x-"
x,"
z+"
0*"
0)"
x("
x'"
x&"
x%"
z$"
0#"
0""
x!"
x~
x}
x|
z{
0z
0y
xx
xw
xv
xu
zt
0s
0r
xq
xp
xo
xn
zm
0l
0k
xj
xi
xh
xg
zf
0e
0d
xc
xb
xa
x`
z_
0^
0]
x\
x[
xZ
xY
zX
0W
0V
xU
xT
xS
xR
zQ
0P
0O
xN
xM
xL
xK
zJ
0I
0H
xG
xF
xE
xD
zC
0B
0A
x@
x?
x>
x=
z<
0;
0:
x9
x8
x7
x6
z5
04
03
bx0 2
bx 1
bx 0
bx /
bx .
bx -
b0 ,
b0 +
0*
b0 )
b0 (
0'
b0 &
b0 %
x$
x#
bx "
bx !
$end
#1
b0 0
b0 .
0R"
0S"
0Y"
0Z"
0`"
0a"
b0 J"
b0 j"
0g"
b0 I"
b0 k"
0h"
0z"
0{"
0##
0$#
0*#
0+#
b0 r"
b0 4#
01#
b0 q"
b0 5#
02#
0D#
0E#
0K#
0L#
0R#
0S#
b0 <#
b0 \#
0Y#
b0 ;#
b0 ]#
0Z#
0l#
0m#
0s#
0t#
0z#
0{#
b0 d#
b0 &$
0#$
b0 c#
b0 '$
0$$
07
08
0>
0?
0E
0F
0L
0M
0S
0T
0Z
0[
0a
0b
0h
0i
0o
0p
0v
0w
0}
0~
0&"
0'"
0-"
0."
04"
05"
0;"
0<"
b0 1
0B"
b0 /
0C"
#2
0Q"
0X"
0_"
0f"
0y"
0"#
0)#
00#
0C#
0J#
0Q#
0X#
0k#
0r#
0y#
0"$
06
0=
0D
0K
0R
0Y
0`
0g
0n
0u
0|
0%"
0,"
03"
0:"
0A"
#3
bz0 u"
0o"
0L"
0t"
0>#
0f#
04$
09$
0>$
0C$
0H$
0M$
0R$
0W$
0\$
0a$
0f$
0k$
0p$
0u$
0z$
0#
bx00 2
b0 K"
b0 l"
b0 s"
b0 6#
b0 =#
b0 ^#
b0 e#
b0 ($
00$
05$
0:$
0?$
0D$
0I$
0N$
0S$
0X$
0]$
0b$
0g$
0l$
0q$
0v$
b0 ,$
0{$
#4
bx0 "
bx0 -
bx0 H"
bx0 !
bx0 +$
01$
#5
bz0 g#
0a#
bz0 ?#
09#
bx0000 2
#7
0$
b0 H"
b0 p"
b0x :#
b0x000x00000000 "
b0x000x00000000 -
b0x b#
06$
0;$
0@$
0E$
0J$
0O$
0T$
0Y$
0^$
0c$
0h$
0m$
0r$
0w$
b0 !
b0 +$
0|$
b0 2
#9
b0 b#
b0 "
b0 -
b0 :#
#10
1/$
bz1 M"
1G"
b1 ,$
1*
b1 2
1'
#14
b1 !
b1 +$
11$
b1 "
b1 -
b1 H"
#20
1O"
1N"
1U"
1\"
1c"
1v"
1}"
1&#
1-#
1@#
1G#
1N#
1U#
1h#
1o#
1v#
1}#
0/$
1.$
1-$
12$
17$
1<$
1A$
1F$
1K$
1P$
1U$
1Z$
1_$
1d$
1i$
1n$
1s$
1x$
bz0 M"
0G"
14
b1 F"
13
1:
1A
1H
1O
1V
1]
1d
1k
1r
1y
1""
1)"
10"
17"
1>"
b1111 E"
b1111 m"
b1111 7#
b1111 _#
b0 ,$
0*
b1 )
b1 *$
b1111111111111111 (
b1111111111111111 )$
b0 2
0'
b1 &
b1 ,
b1111111111111111 %
b1111111111111111 +
#21
b1 0
b1111 .
b1 J"
b1 j"
1R"
1S"
1Z"
1a"
b1111 I"
b1111 k"
1h"
1{"
1$#
1+#
b1111 q"
b1111 5#
12#
1E#
1L#
1S#
b1111 ;#
b1111 ]#
1Z#
1m#
1t#
1{#
b1111 c#
b1111 '$
1$$
b1 1
17
18
1?
1F
1M
1T
1[
1b
1i
1p
1w
1~
1'"
1."
15"
1<"
b1111111111111111 /
1C"
#22
xX"
x_"
xf"
xy"
x"#
x)#
x0#
xC#
xJ#
xQ#
xX#
xk#
xr#
xy#
x"$
x=
xD
xK
xR
xY
x`
xg
xn
xu
x|
x%"
x,"
x3"
x:"
xA"
1Q"
16
#23
bz1 u"
1o"
14$
b10 2
b1 K"
b1 l"
b10 ,$
10$
