Lab6/FPGA_combine.v
module logic_tile(
    out, 
    clock, 
    in1, 
    in2, 
    in3, 
    in4, 
    in5
);
    input in1, in2, in3, in4, in5, clock ;
    output out ;
    reg tem;
    reg tem2;
    initial begin
        tem2 = 1'b0;
    end
    reg out ;
    reg [32:0] mem;
    always @(*) begin
        case({in5, in4, in3, in2, in1})
            5'b00000 : tem = mem[0] ;
            5'b00001 : tem = mem[1] ;
            5'b00010 : tem = mem[2] ;
            5'b00011 : tem = mem[3] ;
            5'b00100 : tem = mem[4] ;
            5'b00101 : tem = mem[5] ;
            5'b00110 : tem = mem[6] ;
            5'b00111 : tem = mem[7] ;
            5'b01000 : tem = mem[8] ;
            5'b01001 : tem = mem[9] ;
            5'b01010 : tem = mem[10] ;
            5'b01011 : tem = mem[11] ;
            5'b01100 : tem = mem[12] ;
            5'b01101 : tem = mem[13] ;
            5'b01110 : tem = mem[14] ;
            5'b01111 : tem = mem[15] ;
            5'b10000 : tem = mem[16] ;
            5'b10001 : tem = mem[17] ;
            5'b10010 : tem = mem[18] ;
            5'b10011 : tem = mem[19] ;
            5'b10100 : tem = mem[20] ;
            5'b10101 : tem = mem[21] ;
            5'b10110 : tem = mem[22] ;
            5'b10111 : tem = mem[23] ;
            5'b11000 : tem = mem[24] ;
            5'b11001 : tem = mem[25] ;
            5'b11010 : tem = mem[26] ;
            5'b11011 : tem = mem[27] ;
            5'b11100 : tem = mem[28] ;
            5'b11101 : tem = mem[29] ;
            5'b11110 : tem = mem[30] ;
            5'b11111 : tem = mem[31] ;
        endcase
    end
    always @(posedge clock) begin
        tem2 = tem;
    end
    always @(*) begin
        case (mem[32])
            1'b0 : out = tem ;
            1'b1 : out = tem2 ;
        endcase
    end
endmodule

module switch_box_4x4(
    out, 
    in
);
    input [3: 0] in ;
    output [3:0] out ;
    reg [15:0] configure ;
    assign out[0] = configure[0]&in[0] | configure[1]&in[1] | configure[2]&in[2] | configure[3]&in[3] ;
    assign out[1] = configure[4]&in[0] | configure[5]&in[1] | configure[6]&in[2] | configure[7]&in[3] ;
    assign out[2] = configure[8]&in[0] | configure[9]&in[1] | configure[10]&in[2] | configure[11]&in[3] ;
    assign out[3] = configure[12]&in[0] | configure[13]&in[1] | configure[14]&in[2] | configure[15]&in[3] ;

endmodule

module master(
    clk,
    in0,
    in1,
    in2, 
    in3, 
    in4, 
    in5, 
    in6, 
    in7,
    cn0,
    cn1,
    cn2,
    cn3,
    out0,
    out1,
    out2,
    out3,
    out4,
    out5,
    out6,
    out7
);
    input in0, in1, in2, in3, in4, in5, in6, in7, cn0, cn1, cn2, cn3, clk;
    output out0, out1, out2, out3, out4, out5, out6, out7 ;
    reg out0, out1, out2, out3, out4, out5, out6, out7 ;
    reg zero = 1'b0;
    wire [3:0] rs0;
    wire [3:0] rs1;
    wire [3:0] rs2;
    wire [3:0] rs3;
    wire [3:0] rs4;
    wire [3:0] rs5;
    wire [3:0] rs6;
    wire [3:0] rs7;
    wire [3:0] rs8;
    wire [3:0] rs9;
    wire [3:0] rs10;
    wire [3:0] rsc;
    wire [3:0] rsf;
    wire ol0;
    wire ol1;
    wire ol2;
    wire ol3;
    wire ol4;
    wire ol5;
    wire ol6;
    wire ol7;
    wire ol8;
    wire ol9;
    wire ol10;
    wire ol11;
    wire ol12;
    wire ol13;
    wire upd_clk ;
    switch_box_4x4 s0(rs0, {zero, ol1, cn0, in4});
    switch_box_4x4 s1(rs1, {ol0, ol2, ol4, in5});
    switch_box_4x4 s2(rs2, {ol1, ol3, ol5, in6});
    switch_box_4x4 s3(rs3, {ol2, ol4, ol6, in7});
    switch_box_4x4 s4(rs4, {ol3, ol5, cn0, in0});
    switch_box_4x4 s5(rs5, {ol4, ol6, ol4, in1});
    switch_box_4x4 s6(rs6, {ol5, ol7, ol5, in2});
    switch_box_4x4 s7(rs7, {ol6, cn3, ol6, in3});
    switch_box_4x4 s8(rs8, {ol3, ol2, ol1, ol0});
    switch_box_4x4 s9(rs9, {ol3, ol2, ol1, ol0});
    switch_box_4x4 s10(rs10, {zero, cn1, cn0, ol7});
    switch_box_4x4 sc(rsc, {cn3, cn2, cn1, cn0});
    switch_box_4x4 sf(rsf, {ol13, ol8, ol12, ol7});
    logic_tile clk_modifier(upd_clk,clk, rsc[0], rsc[1], clk, zero, zero);
    logic_tile l0(ol0, upd_clk, in0, rs0[0], rs0[1], rsc[0], rsc[1] );
    logic_tile l1(ol1, upd_clk, in1, rs1[0], rs1[1], rsc[0], rsc[1] );
    logic_tile l2(ol2, upd_clk, in2, rs2[0], rs2[1], rsc[0], rsc[1] );
    logic_tile l3(ol3, upd_clk, in3, rs3[0], rs3[1], rsc[0], rsc[1] );
    logic_tile l4(ol4, upd_clk, in4, rs4[0], rs4[1], rsc[0], rsc[1] );
    logic_tile l5(ol5, upd_clk, in5, rs5[0], rs5[1], rsc[0], rsc[1] );
    logic_tile l6(ol6, upd_clk, in6, rs6[0], rs6[1], rsc[0], rsc[1] );
    logic_tile l7(ol7, upd_clk, in7, rs7[0], rs7[1], rsc[0], rsc[1] ); 
    logic_tile l8(ol8, upd_clk, rs8[0], rs8[1], rs8[2], rs8[3], rs10[0]);
    logic_tile l9(ol9, upd_clk, rs9[0], rs9[1], rs9[2], rs9[3], rs10[0]);
    logic_tile l10(ol10, upd_clk, rs9[0], rs9[1], rs9[2], rs9[3], rs10[0]);
    logic_tile l11(ol11, upd_clk, rs9[0], rs9[1], rs9[2], rs9[3], rs10[0]);
    logic_tile l12(ol12, upd_clk, rs9[0], rs9[1], rs9[2], rs9[3], rs10[0]);
    logic_tile l13(ol13, upd_clk, ol8, ol9, cn0, zero, zero);
    always @(*) begin
        assign out0 = rsf[1]; 
        assign out1 = ol9;
        assign out2 = ol10;
        assign out3 = ol11;
        assign out4 = ol4;
        assign out5 = ol5;
        assign out6 = ol6;
        assign out7 = rsf[0];
    end
endmodule

Lab6/shifter.v
module testbench(
);
    reg clock = 1'b0;
    always #10 clock = ~clock ;
    reg [7:0] in;
    wire [7:0] out;
    reg shl, sh, l, si;
    reg [31:0] tb_mem [0:13];
    master shifter(clock, in[0], in[1], in[2], in[3], in[4], in[5], in[6], in[7], l, shl, sh, si, out[0], out[1], out[2], out[3], out[4], out[5], out[6], out[7]);
    initial begin
        $readmemh("shift.mem", tb_mem);
        $display("memory is %h , %h , %h , %h , %h, %h, %h, %h", tb_mem[0], tb_mem[1], tb_mem[2], tb_mem[3], tb_mem[4], tb_mem[5], tb_mem[6], tb_mem[7]);
        shifter.s0.configure[15:0] = tb_mem[8];
        shifter.s1.configure[15:0] = tb_mem[8];
        shifter.s2.configure[15:0] = tb_mem[8];
        shifter.s3.configure[15:0] = tb_mem[8];
        shifter.s4.configure[15:0] = tb_mem[8];
        shifter.s5.configure[15:0] = tb_mem[8];
        shifter.s6.configure[15:0] = tb_mem[8];
        shifter.s7.configure[15:0] = tb_mem[8];
        shifter.s8.configure[15:0] = tb_mem[9];
        shifter.s9.configure[15:0] = tb_mem[9];
        shifter.s10.configure[15:0] = tb_mem[10];
        shifter.sc.configure[15:0] = tb_mem[11];
        shifter.sf.configure[15:0] = tb_mem[12];
        shifter.clk_modifier.mem[32] = tb_mem[2];
        shifter.clk_modifier.mem[31:0] = tb_mem[13];
        shifter.l0.mem[31:0] = tb_mem[0];
        shifter.l0.mem[32] = tb_mem[1];
        shifter.l1.mem[31:0] = tb_mem[0];
        shifter.l1.mem[32] = tb_mem[1];
        shifter.l2.mem[31:0] = tb_mem[0];
        shifter.l2.mem[32] = tb_mem[1];
        shifter.l3.mem[31:0] = tb_mem[0];
        shifter.l3.mem[32] = tb_mem[1];
        shifter.l4.mem[31:0] = tb_mem[0];
        shifter.l4.mem[32] = tb_mem[1];
        shifter.l5.mem[31:0] = tb_mem[0];
        shifter.l5.mem[32] = tb_mem[1];
        shifter.l6.mem[31:0] = tb_mem[0];
        shifter.l6.mem[32] = tb_mem[1];
        shifter.l7.mem[31:0] = tb_mem[0];
        shifter.l7.mem[32] = tb_mem[1];
        shifter.l8.mem[31:0] = tb_mem[3];
        shifter.l8.mem[32] = tb_mem[2];
        shifter.l9.mem[31:0] = tb_mem[4];
        shifter.l9.mem[32] = tb_mem[2];
        shifter.l10.mem[31:0] = tb_mem[5];
        shifter.l10.mem[32] = tb_mem[2];
        shifter.l11.mem[31:0] = tb_mem[6];
        shifter.l11.mem[32] = tb_mem[2];
        shifter.l12.mem[31:0] = tb_mem[7];
        shifter.l12.mem[32] = tb_mem[2];
        shifter.l13.mem[31:0] = tb_mem[7];
        shifter.l13.mem[32] = tb_mem[2];
    end
    initial begin
        in = 8'b01001001;
        sh = 1'b0;
        shl = 1'b0;
        l = 1'b1;
        si = 1'b0;
        #17
        $display("LOAD input is %b and output is %b", in, out);
        in = 8'b01011001;
        sh = 1'b1;
        shl = 1'b0;
        l = 1'b0;
        si = 1'b1;
        #16
        $display("SHIFT LEFT input is %b and output is %b", in, out);
        in = 8'b01001001;
        sh = 1'b0;
        shl = 1'b1;
        l = 1'b0;
        si = 1'b1;
        #16
        $display("SHIFT RIGHT si= %b input is %b and output is %b",si, in, out);
        in = 8'b01001001;
        sh = 1'b0;
        shl = 1'b0;
        l = 1'b0;
        si = 1'b0;
        #16
        $display("NO CHANGE input is %b and output is %b", in, out);
        in = 8'b11111111;
        sh = 1'b0;
        shl = 1'b0;
        l = 1'b1;
        si = 1'b0;
        #16
        $display("LOAD input is %b and output is %b", in, out);
        in = 8'b01001001;
        sh = 1'b0;
        shl = 1'b1;
        l = 1'b0;
        si = 1'b0;
        #16
        $display("SHIFT RIGHT si= %b input is %b and output is %b",si, in, out);
        in = 8'b01001001;
        sh = 1'b0;
        shl = 1'b1;
        l = 1'b0;
        si = 1'b0;
        #16
        $display("SHIFT RIGHT si= %b input is %b and output is %b",si, in, out);
        in = 8'b01011001;
        sh = 1'b1;
        shl = 1'b0;
        l = 1'b0;
        si = 1'b1;
        #16
        $display("SHIFT LEFT input is %b and output is %b", in, out);
        in = 8'b01011001;
        sh = 1'b1;
        shl = 1'b0;
        l = 1'b0;
        si = 1'b1;
        #16
        $display("SHIFT LEFT input is %b and output is %b", in, out);
        in = 8'b01011001;
        sh = 1'b1;
        shl = 1'b0;
        l = 1'b0;
        si = 1'b1;
        #16
        $display("SHIFT LEFT input is %b and output is %b", in, out);
        in = 8'b01011001;
        sh = 1'b1;
        shl = 1'b0;
        l = 1'b0;
        si = 1'b1;
        #16
        $display("SHIFT LEFT input is %b and output is %b", in, out);
        $finish;
    end
    initial
    begin
        $dumpfile("dump.vcd");
        $dumpvars;
    end
endmodule

Lab6/dump.vcd
$date
	Thu Nov 26 11:52:05 2020
$end
$version
	Icarus Verilog
$end
$timescale
	1s
$end
$scope module testbench $end
$var wire 8 ! out [7:0] $end
$var reg 1 " clock $end
$var reg 8 # in [7:0] $end
$var reg 1 $ l $end
$var reg 1 % sh $end
$var reg 1 & shl $end
$var reg 1 ' si $end
$scope module shifter $end
$var wire 1 " clk $end
$var wire 1 $ cn0 $end
$var wire 1 & cn1 $end
$var wire 1 % cn2 $end
$var wire 1 ' cn3 $end
$var wire 1 ( in0 $end
$var wire 1 ) in1 $end
$var wire 1 * in2 $end
$var wire 1 + in3 $end
$var wire 1 , in4 $end
$var wire 1 - in5 $end
$var wire 1 . in6 $end
$var wire 1 / in7 $end
$var wire 1 0 upd_clk $end
$var wire 4 1 rsf [3:0] $end
$var wire 4 2 rsc [3:0] $end
$var wire 4 3 rs9 [3:0] $end
$var wire 4 4 rs8 [3:0] $end
$var wire 4 5 rs7 [3:0] $end
$var wire 4 6 rs6 [3:0] $end
$var wire 4 7 rs5 [3:0] $end
$var wire 4 8 rs4 [3:0] $end
$var wire 4 9 rs3 [3:0] $end
$var wire 4 : rs2 [3:0] $end
$var wire 4 ; rs10 [3:0] $end
$var wire 4 < rs1 [3:0] $end
$var wire 4 = rs0 [3:0] $end
$var wire 1 > ol9 $end
$var wire 1 ? ol8 $end
$var wire 1 @ ol7 $end
$var wire 1 A ol6 $end
$var wire 1 B ol5 $end
$var wire 1 C ol4 $end
$var wire 1 D ol3 $end
$var wire 1 E ol2 $end
$var wire 1 F ol13 $end
$var wire 1 G ol12 $end
$var wire 1 H ol11 $end
$var wire 1 I ol10 $end
$var wire 1 J ol1 $end
$var wire 1 K ol0 $end
$var reg 1 L out0 $end
$var reg 1 M out1 $end
$var reg 1 N out2 $end
$var reg 1 O out3 $end
$var reg 1 P out4 $end
$var reg 1 Q out5 $end
$var reg 1 R out6 $end
$var reg 1 S out7 $end
$var reg 1 T zero $end
$scope module clk_modifier $end
$var wire 1 " clock $end
$var wire 1 U in1 $end
$var wire 1 V in2 $end
$var wire 1 " in3 $end
$var wire 1 T in4 $end
$var wire 1 T in5 $end
$var reg 33 W mem [32:0] $end
$var reg 1 0 out $end
$var reg 1 X tem $end
$var reg 1 Y tem2 $end
$upscope $end
$scope module l0 $end
$var wire 1 0 clock $end
$var wire 1 ( in1 $end
$var wire 1 Z in2 $end
$var wire 1 [ in3 $end
$var wire 1 \ in4 $end
$var wire 1 ] in5 $end
$var reg 33 ^ mem [32:0] $end
$var reg 1 K out $end
$var reg 1 _ tem $end
$var reg 1 ` tem2 $end
$upscope $end
$scope module l1 $end
$var wire 1 0 clock $end
$var wire 1 ) in1 $end
$var wire 1 a in2 $end
$var wire 1 b in3 $end
$var wire 1 c in4 $end
$var wire 1 d in5 $end
$var reg 33 e mem [32:0] $end
$var reg 1 J out $end
$var reg 1 f tem $end
$var reg 1 g tem2 $end
$upscope $end
$scope module l10 $end
$var wire 1 0 clock $end
$var wire 1 h in1 $end
$var wire 1 i in2 $end
$var wire 1 j in3 $end
$var wire 1 k in4 $end
$var wire 1 l in5 $end
$var reg 33 m mem [32:0] $end
$var reg 1 I out $end
$var reg 1 n tem $end
$var reg 1 o tem2 $end
$upscope $end
$scope module l11 $end
$var wire 1 0 clock $end
$var wire 1 p in1 $end
$var wire 1 q in2 $end
$var wire 1 r in3 $end
$var wire 1 s in4 $end
$var wire 1 t in5 $end
$var reg 33 u mem [32:0] $end
$var reg 1 H out $end
$var reg 1 v tem $end
$var reg 1 w tem2 $end
$upscope $end
$scope module l12 $end
$var wire 1 0 clock $end
$var wire 1 x in1 $end
$var wire 1 y in2 $end
$var wire 1 z in3 $end
$var wire 1 { in4 $end
$var wire 1 | in5 $end
$var reg 33 } mem [32:0] $end
$var reg 1 G out $end
$var reg 1 ~ tem $end
$var reg 1 !" tem2 $end
$upscope $end
$scope module l13 $end
$var wire 1 0 clock $end
$var wire 1 $ in3 $end
$var wire 1 T in4 $end
$var wire 1 T in5 $end
$var wire 1 > in2 $end
$var wire 1 ? in1 $end
$var reg 33 "" mem [32:0] $end
$var reg 1 F out $end
$var reg 1 #" tem $end
$var reg 1 $" tem2 $end
$upscope $end
$scope module l2 $end
$var wire 1 0 clock $end
$var wire 1 * in1 $end
$var wire 1 %" in2 $end
$var wire 1 &" in3 $end
$var wire 1 '" in4 $end
$var wire 1 (" in5 $end
$var reg 33 )" mem [32:0] $end
$var reg 1 E out $end
$var reg 1 *" tem $end
$var reg 1 +" tem2 $end
$upscope $end
$scope module l3 $end
$var wire 1 0 clock $end
$var wire 1 + in1 $end
$var wire 1 ," in2 $end
$var wire 1 -" in3 $end
$var wire 1 ." in4 $end
$var wire 1 /" in5 $end
$var reg 33 0" mem [32:0] $end
$var reg 1 D out $end
$var reg 1 1" tem $end
$var reg 1 2" tem2 $end
$upscope $end
$scope module l4 $end
$var wire 1 0 clock $end
$var wire 1 , in1 $end
$var wire 1 3" in2 $end
$var wire 1 4" in3 $end
$var wire 1 5" in4 $end
$var wire 1 6" in5 $end
$var reg 33 7" mem [32:0] $end
$var reg 1 C out $end
$var reg 1 8" tem $end
$var reg 1 9" tem2 $end
$upscope $end
$scope module l5 $end
$var wire 1 0 clock $end
$var wire 1 - in1 $end
$var wire 1 :" in2 $end
$var wire 1 ;" in3 $end
$var wire 1 <" in4 $end
$var wire 1 =" in5 $end
$var reg 33 >" mem [32:0] $end
$var reg 1 B out $end
$var reg 1 ?" tem $end
$var reg 1 @" tem2 $end
$upscope $end
$scope module l6 $end
$var wire 1 0 clock $end
$var wire 1 . in1 $end
$var wire 1 A" in2 $end
$var wire 1 B" in3 $end
$var wire 1 C" in4 $end
$var wire 1 D" in5 $end
$var reg 33 E" mem [32:0] $end
$var reg 1 A out $end
$var reg 1 F" tem $end
$var reg 1 G" tem2 $end
$upscope $end
$scope module l7 $end
$var wire 1 0 clock $end
$var wire 1 / in1 $end
$var wire 1 H" in2 $end
$var wire 1 I" in3 $end
$var wire 1 J" in4 $end
$var wire 1 K" in5 $end
$var reg 33 L" mem [32:0] $end
$var reg 1 @ out $end
$var reg 1 M" tem $end
$var reg 1 N" tem2 $end
$upscope $end
$scope module l8 $end
$var wire 1 0 clock $end
$var wire 1 O" in1 $end
$var wire 1 P" in2 $end
$var wire 1 Q" in3 $end
$var wire 1 R" in4 $end
$var wire 1 S" in5 $end
$var reg 33 T" mem [32:0] $end
$var reg 1 ? out $end
$var reg 1 U" tem $end
$var reg 1 V" tem2 $end
$upscope $end
$scope module l9 $end
$var wire 1 0 clock $end
$var wire 1 W" in1 $end
$var wire 1 X" in2 $end
$var wire 1 Y" in3 $end
$var wire 1 Z" in4 $end
$var wire 1 [" in5 $end
$var reg 33 \" mem [32:0] $end
$var reg 1 > out $end
$var reg 1 ]" tem $end
$var reg 1 ^" tem2 $end
$upscope $end
$scope module s0 $end
$var wire 4 _" in [3:0] $end
$var wire 4 `" out [3:0] $end
$var reg 16 a" configure [15:0] $end
$upscope $end
$scope module s1 $end
$var wire 4 b" in [3:0] $end
$var wire 4 c" out [3:0] $end
$var reg 16 d" configure [15:0] $end
$upscope $end
$scope module s10 $end
$var wire 4 e" in [3:0] $end
$var wire 4 f" out [3:0] $end
$var reg 16 g" configure [15:0] $end
$upscope $end
$scope module s2 $end
$var wire 4 h" in [3:0] $end
$var wire 4 i" out [3:0] $end
$var reg 16 j" configure [15:0] $end
$upscope $end
$scope module s3 $end
$var wire 4 k" in [3:0] $end
$var wire 4 l" out [3:0] $end
$var reg 16 m" configure [15:0] $end
$upscope $end
$scope module s4 $end
$var wire 4 n" in [3:0] $end
$var wire 4 o" out [3:0] $end
$var reg 16 p" configure [15:0] $end
$upscope $end
$scope module s5 $end
$var wire 4 q" in [3:0] $end
$var wire 4 r" out [3:0] $end
$var reg 16 s" configure [15:0] $end
$upscope $end
$scope module s6 $end
$var wire 4 t" in [3:0] $end
$var wire 4 u" out [3:0] $end
$var reg 16 v" configure [15:0] $end
$upscope $end
$scope module s7 $end
$var wire 4 w" in [3:0] $end
$var wire 4 x" out [3:0] $end
$var reg 16 y" configure [15:0] $end
$upscope $end
$scope module s8 $end
$var wire 4 z" in [3:0] $end
$var wire 4 {" out [3:0] $end
$var reg 16 |" configure [15:0] $end
$upscope $end
$scope module s9 $end
$var wire 4 }" in [3:0] $end
$var wire 4 ~" out [3:0] $end
$var reg 16 !# configure [15:0] $end
$upscope $end
$scope module sc $end
$var wire 4 "# in [3:0] $end
$var wire 4 ## out [3:0] $end
$var reg 16 $# configure [15:0] $end
$upscope $end
$scope module sf $end
$var wire 4 %# in [3:0] $end
$var wire 4 &# out [3:0] $end
$var reg 16 '# configure [15:0] $end
$upscope $end
$upscope $end
$upscope $end
$enddefinitions $end
#0
$dumpvars
b1000001 '#
b0 &#
b0 %#
b1100101 $#
b1 ##
b1 "#
b1000010000100001 !#
b0 ~"
b0 }"
b1000010000100001 |"
b0 {"
b0 z"
b1001000 y"
b0 x"
b1 w"
b1001000 v"
b0 u"
b0 t"
b1001000 s"
b0 r"
b0 q"
b1001000 p"
b0 o"
b11 n"
b1001000 m"
b0 l"
b0 k"
b1001000 j"
b0 i"
b1 h"
b0 g"
b0 f"
b10 e"
b1001000 d"
b0 c"
b0 b"
b1001000 a"
b0 `"
b10 _"
0^"
0]"
b11001100110011001100110011001100 \"
0["
0Z"
0Y"
0X"
0W"
0V"
0U"
b10101010101010101010101010101010 T"
0S"
0R"
0Q"
0P"
0O"
0N"
0M"
b111001100111100001010101000000000 L"
0K"
1J"
0I"
0H"
0G"
1F"
b111001100111100001010101000000000 E"
0D"
1C"
0B"
0A"
0@"
0?"
b111001100111100001010101000000000 >"
0="
1<"
0;"
0:"
09"
08"
b111001100111100001010101000000000 7"
06"
15"
04"
03"
02"
11"
b111001100111100001010101000000000 0"
0/"
1."
0-"
0,"
0+"
0*"
b111001100111100001010101000000000 )"
0("
1'"
0&"
0%"
0$"
0#"
b0 ""
0!"
0~
b0 }
0|
0{
0z
0y
0x
0w
0v
b11111111000000001111111100000000 u
0t
0s
0r
0q
0p
0o
0n
b11110000111100001111000011110000 m
0l
0k
0j
0i
0h
0g
0f
b111001100111100001010101000000000 e
0d
1c
0b
0a
0`
1_
b111001100111100001010101000000000 ^
0]
1\
0[
0Z
0Y
0X
b11100000 W
0V
1U
0T
0S
0R
0Q
0P
0O
0N
0M
0L
0K
0J
0I
0H
0G
0F
0E
0D
0C
0B
0A
0@
0?
0>
b0 =
b0 <
b0 ;
b0 :
b0 9
b0 8
b0 7
b0 6
b0 5
b0 4
b0 3
b1 2
b0 1
00
0/
1.
0-
0,
1+
0*
0)
1(
0'
0&
0%
1$
b1001001 #
0"
b0 !
$end
#10
1L
b10 1
b10 &#
b100 %#
1?
1U"
1x
1p
1h
1W"
1O"
1O
1H
1v
1&"
1;"
1a
1{
1s
1k
1Z"
1R"
13"
b10 :
b10 i"
1H"
b10 7
b10 r"
b1 <
b1 c"
b1001 3
b1001 ~"
b1001 4
b1001 {"
b1 8
b1 o"
b1 5
b1 x"
b1000 b"
1K
b1001 }"
b1001 z"
b1011 n"
b101 h"
1D
b1011 w"
b100 q"
b10 k"
b1001001 !
1R
1A
1`
12"
1G"
10
1Y
1X
1"
#17
1M"
0F"
01"
1f
0_
1I"
1K"
1D"
1="
16"
1/"
1("
1d
1]
1V
b11 5
b11 x"
b11 2
b11 ##
18"
1,
b1111 w"
1'
b1 _"
b1001 n"
b0 e"
0$
b1100 "#
1%
b1011001 #
#20
00
0X
0"
#30
0L
1M
1>
0?
1]"
0U"
1S
0O
0H
1y
1q
1i
1X"
1P"
0x
0p
0h
0W"
0O"
b1 1
b1 &#
1B"
0M"
0;"
1?"
1-"
0v
08"
0&"
1*"
1[
0f
b10 6
b10 u"
0H"
1:"
b10 9
b10 l"
0{
0s
0k
0Z"
0R"
03"
1%"
b10 =
b10 `"
0a
b10 5
b10 x"
b1 7
b1 r"
b10 3
b10 ~"
b10 4
b10 {"
b0 8
b0 o"
b1 :
b1 i"
b0 <
b0 c"
b1 %#
b1 e"
b100 t"
1@
b101 w"
0R
0A
b1010 q"
b100 k"
b10010010 !
1P
1C
b1 n"
0D
b1001 h"
b101 _"
1J
b10 }"
b10 z"
b10 b"
0K
1w
1V"
1N"
0G"
19"
02"
1g
0`
10
1X
1"
#33
1L
b11 1
b11 &#
0M
0>
b101 %#
1?
0]"
1U"
1x
1p
1h
1W"
1O"
0y
0q
0i
0X"
0P"
1O
1H
0[
1v
1&"
0-"
1;"
1a
0%"
b0 =
b0 `"
1{
1s
1k
1Z"
1R"
13"
0:"
b0 9
b0 l"
1H"
b1 <
b1 c"
b10 :
b10 i"
b1001 3
b1001 ~"
b1001 4
b1001 {"
b1 8
b1 o"
b10 7
b10 r"
b11 5
b11 x"
1K
0J
b1001 }"
b1001 z"
b1001 n"
b101 h"
1D
b1000 b"
0P
0C
b1111 w"
b100 q"
b10 k"
b11001001 !
1R
1A
1`
0g
12"
09"
1G"
0V"
1^"
0w
1M"
1F"
01"
0_
10
1?"
1*"
1X
0J"
0C"
0<"
05"
0."
0'"
0c
0\
0U
1K"
1D"
1="
16"
1/"
1("
1d
1]
1V
b10 2
b10 ##
b0 _"
0,
b101 e"
1&
b1010 "#
0%
b1001001 #
#40
00
0X
0"
#49
0F"
0?"
0*"
0M"
0K"
0D"
0="
06"
0/"
0("
0d
0]
0V
0I"
b0 2
b0 ##
b1 5
b1 x"
b1011 w"
0'
b1 e"
b0 "#
0&
#50
0Y
1"
#60
0"
#65
1M"
1F"
1?"
18"
11"
1*"
1f
1_
1J"
1C"
1<"
15"
1."
1'"
1c
1\
1U
b1 2
b1 ##
b101 q"
1)
b101 t"
1*
1,
b1001 b"
1-
b11 k"
1/
b11 _"
b1011 n"
b11 e"
b1 "#
1$
b11111111 #
#70
1N
1I
1M
1>
1n
1]"
1y
1q
1i
1X"
1P"
14"
1-"
1z
1r
1j
1Y"
1Q"
1b
1[
1A"
b11 8
b11 o"
1:"
b1111 3
b1111 ~"
b1111 4
b1111 {"
1,"
b11 <
b11 c"
1%"
b10 =
b10 `"
b11 6
b11 u"
b11 7
b11 r"
b11 9
b11 l"
b11 :
b11 i"
b1111 t"
b1111 n"
1Q
1B
b1111 q"
b11111111 !
1P
1C
b1111 k"
b1111 b"
1E
b1111 }"
b1111 z"
b1111 h"
b111 _"
1J
1w
0^"
1V"
1@"
19"
1+"
1g
10
1Y
1X
1"
#80
00
0X
0"
#81
0J"
0C"
0<"
05"
0."
0'"
0c
0\
0U
1K"
1D"
1="
16"
1/"
1("
1d
1]
1V
b10 2
b10 ##
1f
1*"
18"
1?"
0M"
b1110 q"
0)
b1110 t"
0*
0,
b1110 b"
0-
b1110 k"
0/
b100 _"
b1101 n"
0$
b101 e"
b10 "#
1&
b1001001 #
#90
b1111111 !
0S
0F"
b10 1
b10 &#
0B"
b1 6
b1 u"
b100 %#
b100 e"
b1010 t"
0@
0N"
1^"
1o
10
1X
1"
#100
00
0X
0"
#110
0?"
0;"
0H"
b1 7
b1 r"
b0 5
b0 x"
b1 w"
b1010 q"
b1100 k"
b111111 !
0R
0A
0G"
10
1X
1"
#113
1F"
1?"
0_
1I"
1J"
1C"
1<"
15"
1."
1'"
1c
1\
1U
b10 5
b10 x"
b11 2
b11 ##
b101 _"
1,
b101 w"
1'
b0 e"
0&
b1100 "#
1%
b1011001 #
#120
00
0X
0"
#130
0L
b0 1
b0 &#
b0 %#
0?
0U"
0x
0p
0h
0W"
0O"
b1110 3
b1110 ~"
b1110 4
b1110 {"
0f
1M"
1;"
0a
1H"
b11 7
b11 r"
b10 <
b10 c"
b11 5
b11 x"
b1110 }"
b1110 z"
b110 b"
0K
b1111 w"
b1110 q"
b1110 k"
b1111110 !
1R
1A
0`
1G"
10
1X
1"
#140
00
0X
0"
#150
0M
0>
0]"
b11111100 !
1S
0y
0q
0i
0X"
0P"
b1 1
b1 &#
1B"
b1100 3
b1100 ~"
b1100 4
b1100 {"
0*"
0[
b11 6
b11 u"
0%"
b0 =
b0 `"
b10 :
b10 i"
b1 %#
b1 e"
b1110 t"
1@
b1100 }"
b1100 z"
b111 h"
b1 _"
0J
0V"
1N"
0g
10
1X
1"
#160
00
0X
0"
#170
b11111000 !
0N
0I
0n
0z
0r
0j
0Y"
0Q"
01"
0b
b1000 3
b1000 ~"
b1000 4
b1000 {"
0,"
b0 <
b0 c"
b10 9
b10 l"
b1000 }"
b1000 z"
b110 k"
b10 b"
0E
0+"
0^"
10
1X
1"
